discrete_fuzzy_operators/base/decision_making/discrete_fuzzy_numbers/discrete_fuzzy_number.py
discrete_fuzzy_operators/base/decision_making/two_tuple/linguistic_term_set.py
discrete_fuzzy_operators/base/decision_making/two_tuple/two_tuple.py
discrete_fuzzy_operators/base/exceptions/decision_making/discrete_fuzzy_numbers/dfn_bad_dimension.py
discrete_fuzzy_operators/base/exceptions/decision_making/discrete_fuzzy_numbers/dfn_membership_out_bounds.py
discrete_fuzzy_operators/base/exceptions/decision_making/owa/owa_bad_weight_definition.py
discrete_fuzzy_operators/base/exceptions/decision_making/owa/owa_bad_weight_length.py
discrete_fuzzy_operators/base/exceptions/decision_making/two_tuple/two_tuple_bad_operation.py
discrete_fuzzy_operators/base/exceptions/operators/operator_bad_definition.py
discrete_fuzzy_operators/base/exceptions/operators/operator_range_invalid.py
discrete_fuzzy_operators/base/exceptions/operators/operator_size_exception.py
discrete_fuzzy_operators/base/operators/binary_operators/fuzzy_discrete_binary_operator.py
discrete_fuzzy_operators/base/operators/binary_operators/suboperators/fuzzy_aggregation_operator.py
discrete_fuzzy_operators/base/operators/binary_operators/suboperators/fuzzy_implication_operator.py
discrete_fuzzy_operators/base/operators/binary_operators/suboperators/fuzzy_aggregation_suboperators/conjunction.py
discrete_fuzzy_operators/base/operators/binary_operators/suboperators/fuzzy_aggregation_suboperators/copula.py
discrete_fuzzy_operators/base/operators/binary_operators/suboperators/fuzzy_aggregation_suboperators/disjunction.py
discrete_fuzzy_operators/base/operators/binary_operators/suboperators/fuzzy_aggregation_suboperators/nullnorm.py
discrete_fuzzy_operators/base/operators/binary_operators/suboperators/fuzzy_aggregation_suboperators/quasi_copula.py
discrete_fuzzy_operators/base/operators/binary_operators/suboperators/fuzzy_aggregation_suboperators/tconorm.py
discrete_fuzzy_operators-1.8.1.dist-info/LICENSE.txt
discrete_fuzzy_operators-1.8.1.dist-info/METADATA
discrete_fuzzy_operators-1.8.1.dist-info/WHEEL
discrete_fuzzy_operators-1.8.1.dist-info/top_level.txt
discrete_fuzzy_operators-1.8.1.dist-info/RECORD
