Metadata-Version: 2.1
Name: discrete-fuzzy-operators
Version: 1.8.1
Summary: Pure Python implementation of the main fuzzy discrete operators defined in a finite chain
Home-page: https://github.com/mmunar97/discrete-fuzzy-operators
Author: marcmunar
Author-email: marc.munar@uib.es
License: mit
Keywords: discrete fuzzy operators,discrete connectives,discrete fuzzy numbers,ordinal decision making
Platform: UNKNOWN
License-File: LICENSE.txt
Requires-Dist: numpy
Requires-Dist: plotly
Requires-Dist: pandas
Requires-Dist: numba
